{
  "cover": "/images/uploads/coffret_2020_web.jpg",
  "title": "Artefacts",
  "soustitre": "Coffret 2020",
  "date": "2020/07/26",
  "body": {
    "description": "### Éditions Filigranes\n\n**AUTEUR.E.S:** Émeric Lhuisset, Coline Jourdan, Lucía Peluffo\\\n**TEXTES:** Fabien Ribery\n\nFormat: 170 x 250 mm\\\nLangues: Français/Anglais\\\nPrix: 25,00 €\\\nTirage: 500 exemplaires\\\nISBN: 978-2-35046-520-3",
    "commander": [
      {
        "linktexte": "COMMANDER ",
        "linklien": "https://www.filigranes.com/livre/12-artefactes/"
      }
    ],
    "content": "**\\#13 «Le bruit du silence»** (Émeric Lhuisset)\n**\\#14 «Soulever la poussière»** (Coline Jourdan)\n**\\#15 «Une tentative d’équilibre»** (Lucía Peluffo)\n\n**Extraits des textes de Fabien Ribery**\n\n**Émeric Lhuisset**\n\n_Time is out joint, écrivait dans Hamlet William Shakespeare. Le temps est désaccordé, désarrimé, désajointé, désoeuvré, désorienté. Plus que jamais, l’avenir est incertain, entre catastrophe écosystémique diagnostiqué comme nouvelle disparition des espèces sur une planète Terre rendu exsangue par les ravages de l’extractivisme et du consumérisme de masse (anthropocène), et invention d’une pensée collective inédite, à la hauteur d’un effondrement perçu par chacun._ \n\n**Coline Jourdan**\n\n_On peut marcher longtemps dans le paysage, s’enchanter d’un cours d’eau, pique-niquer dans la clairière d’un bois, sans se rendre compte que l’endroit, comme beaucoup d’autres désormais, est devenu invivable, qu’il est maléficié. Ce sont des lieux de scandales sanitaires invisibles, fruits pourris de l’exploitation industrielle de la terre et de l’inconséquence humaine. En lui faisant rendre gorge, en lui extorquant sa matière, en la profanant sans aucune conscience de son unité fondamentale, nous lui imposons une détresse bientôt transmise aux promeneurs insouciants se trouvant dans le périmètre de son démembrement._ \n\n**Lucía Peluffo**\n\n_“Ce que l’homme a de plus de profond, c’est la peau” écrivait Paul Valéry dans une formule aussi définitive que paradoxale. \nParce que la peau n’est pas que frontière, sorte d’interface neutre entre les espaces du dehors et ceux du dedans, mais parce qu’elle est langage fondamental, expression, écriture. On cherche souvent l’âme dans quelque région éthérée de l’être, mais il se pourrait bien qu’elle soit simplement là, tout près de nous, contre nous, en nous, dans la peau que nous pinçons pour nous assurer que nous ne rêvons pas, dans les cellules de notre corps._",
    "savoirplus": [
      {
        "linktexte": "RÉSIDENCE 2020",
        "linklien": "https://www.1plus2.fr/residences/r%C3%A9sidence-2020/"
      }
    ],
    "link": [
      {
        "linktexte": "Éditions Filigranes",
        "linklien": "http://www.filigranes.com"
      }
    ]
  },
  "galeries": {
    "images": [
      {
        "image": "/images/uploads/2020_coffret_artefacts001.jpg",
        "alt": "© Résidence 1+2, coffret Artefacts, 2020."
      },
      {
        "image": "/images/uploads/2020_coffret_artefacts002.jpg",
        "alt": "© Résidence 1+2, coffret Artefacts, 2020."
      },
      {
        "image": "/images/uploads/2020_coffret_artefacts003.jpg",
        "alt": "© Résidence 1+2, coffret Artefacts, 2020."
      },
      {
        "image": "/images/uploads/2020_coffret_artefacts006.jpg",
        "alt": "© Résidence 1+2, couverture de l'ouvrage \"Le bruit du silence\", coffret Artefacts, 2020."
      },
      {
        "image": "/images/uploads/2020_coffret_artefacts005.jpg",
        "alt": "© Résidence 1+2, couverture de l'ouvrage \"Soulever la poussière\", coffret Artefacts, 2020."
      },
      {
        "image": "/images/uploads/2020_coffret_artefacts004.jpg",
        "alt": "© Résidence 1+2, couverture de l'ouvrage \"Une tentative d'équilibre\", coffret Artefacts, 2020."
      },
      {
        "image": "/images/uploads/emeric-ouvrage_1.jpg",
        "alt": "© Émeric Lhuisset, extrait de l'ouvrage \"Le bruit du silence\", coffret Artefacts, 2020."
      },
      {
        "image": "/images/uploads/coline-ouvrage_1.jpg",
        "alt": "© Coline Jourdan, extrait de l'ouvrage \"Soulever la poussière\", coffret Artefacts, 2020."
      },
      {
        "image": "/images/uploads/lucia-ouvrage_1.jpg",
        "alt": "© Lucía Peluffo, extrait de l'ouvrage \"Une tentative d'équilibre\", coffret Artefacts, 2020."
      }
    ]
  },
  "seo": {
    "descriptionseo": "Coffret 2020\nÉditions Filigranes\nAUTEUR.E.S: Émeric Lhuisset, Coline Jourdan, Lucía Peluffo\\\nTEXTES: Fabien Ribery",
    "thumbnail": "/images/uploads/coffret_2020_web.jpg"
  }
}